generateGUID/__init__.py
generateGUID/generate_GUID.py
generateGUID/strip_accents.py
generateGUID/scripts/__init__.py
generateGUID/scripts/generate_GUID_Bash.py
generateGUID/scripts/generate_GUID_Bash_ARGS.py
generateGUID/scripts/generate_GUID_Bash_CSV.py
generateGUID/tests/__init__.py
generateGUID/tests/test_GUID.py
generateGUID/tests/test_GUID2.py
generateGUID/tests/test_GUID_Bash.py
generateGUID-1.4.3.dist-info/LICENSE
generateGUID-1.4.3.dist-info/METADATA
generateGUID-1.4.3.dist-info/WHEEL
generateGUID-1.4.3.dist-info/top_level.txt
generateGUID-1.4.3.dist-info/RECORD
