Metadata-Version: 2.1
Name: generateGUID
Version: 1.4.3
Summary: UNKNOWN
Home-page: https://github.com/Slowblitz/GUID-core
Author: jeremy garcia
Author-email: jeremy.garcia@univ-amu.fr
License: UNKNOWN
Platform: UNKNOWN
Classifier: Programming Language :: Python :: 3
Classifier: License :: OSI Approved :: MIT License
Classifier: Operating System :: OS Independent
